cs/urlutils.py
cs.urlutils-20231129.dist-info/METADATA
cs.urlutils-20231129.dist-info/WHEEL
cs.urlutils-20231129.dist-info/top_level.txt
cs.urlutils-20231129.dist-info/RECORD
