Metadata-Version: 2.1
Name: cs.urlutils
Version: 20231129
Summary: convenience functions for working with URLs
Home-page: https://bitbucket.org/cameron_simpson/css/commits/all
Author: Cameron Simpson
Author-email: Cameron Simpson <cs@cskk.id.au>
License: GNU General Public License v3 or later (GPLv3+)
Project-URL: URL, https://bitbucket.org/cameron_simpson/css/commits/all
Keywords: python3
Classifier: Programming Language :: Python
Classifier: Programming Language :: Python :: 3
Classifier: Development Status :: 4 - Beta
Classifier: Intended Audience :: Developers
Classifier: Operating System :: OS Independent
Classifier: Topic :: Software Development :: Libraries :: Python Modules
Classifier: License :: OSI Approved :: GNU General Public License v3 or later (GPLv3+)
Requires-Dist: beautifulsoup4
Requires-Dist: cs.lex >=20231018
Requires-Dist: cs.logutils >=20230212
Requires-Dist: cs.rfc2616 >=20160828
Requires-Dist: cs.threads >=20231129
